[{"id":"bdccfc76-797e-4615-ba96-0cb63101d46c","title":"Iphone 10","description":"Descripción de iphone","code":"10","price":"990000","status":true,"stock":"100","category":"Apple","thumbnails":[]},{"id":"b0d2ba10-1711-4a31-a5c4-f510a4ad0985","title":"Samsung S20","description":"Lorem impsum","code":"Boom","price":"500000","status":true,"stock":"50","category":"Samsung","thumbnails":[]},{"id":"b9eacce8-11a6-42b9-8542-2fd1fba0a53e","title":"Amd Ryzen 5400","description":"Tarjeta Gráfica","code":"GPUS","price":"4000000","status":true,"stock":"10","category":"Tarjetas Gráficas","thumbnails":[]}]